Workbook

Sheet Read Me
B1: Charticks - Execution Terminal
B2: Manual Test Suite v1.0
B4: Prepared for | C4: Charticks test team
B5: Build under test | C5: Charticks 0.1.0 (Electron + React renderer over the Python sidecar engine)
B6: Suite size | C6: 184 test cases across 20 modules
B7: Date issued | C7: 2026-08-05
B9: HOW TO USE THIS WORKBOOK
B10: 1. | C10: Work through the 'Test Cases' sheet top to bottom. It is ordered so setup comes first and the full regression cycle comes last.
B11: 2. | C11: Read the Pre-condition column FIRST. If you cannot meet it, mark the case 'Blocked' and say why in Remarks - do not guess.
B12: 3. | C12: Follow the Test Steps exactly and in order. Use the values in the Test Data column where one is given.
B13: 4. | C13: Write what actually happened in 'Actual Result' - even when it passes. 'Works' is not enough; write the numbers you saw.
B14: 5. | C14: Set Status from the dropdown. If it is Fail, raise a row in the 'Defect Log' sheet and put its ID in Remarks.
B15: 6. | C15: Attach a screenshot for every Fail. Crop or blur anything showing broker credentials.
B17: STATUS MEANINGS
B18: Pass | C18: The actual result matched the expected result exactly.
B19: Fail | C19: The actual result differed from the expected result. Raise a defect.
B20: Blocked | C20: The test could not be run (pre-condition unavailable, or an earlier defect prevents it).
B21: Not Run | C21: Not attempted yet.
B22: N/A | C22: The case does not apply to this build.
B24: SEVERITY GUIDE (for failures)
B25: Critical | C25: Money at risk: wrong quantity, wrong price, wrong side, an order that should have been blocked but was placed, or data loss.
B26: High | C26: A core function does not work, or a number shown to the trader is wrong.
B27: Medium | C27: A feature works but behaves incorrectly in a specific case.
B28: Low | C28: Cosmetic, wording, or layout.
B30: IMPORTANT SAFETY RULES
B31: Paper mode | C31: Run the WHOLE suite in Paper mode unless a case explicitly says Live. The badge in the status bar must read 'Paper'.
B32: Live mode | C32: Only test Live mode with a broker account you are authorised to trade, using the smallest possible size. Live cases are marked in the Module column.
B33: Market hours | C33: Indian equity derivatives trade 09:15-15:30 IST, Mon-Fri. Many cases need the market OPEN; the market-hours cases need it CLOSED. Plan your day around this.
B34: Credentials | C34: Never share broker credentials, and never include them in a screenshot, a log file or a defect report.
B36: ENVIRONMENT TO RECORD
C37: Before you start, note: Windows version, Charticks version, Python version, broker used, and whether you tested during or outside market hours.

Sheet Test Cases
A1: TC ID | B1: Module | C1: Sub-Module | D1: Test Case Title | E1: Priority | F1: Type | G1: Pre-condition | H1: Test Steps | I1: Test Data | J1: Expected Result | K1: Actual Result | L1: Status | M1: Severity | N1: Tested By | O1: Date | P1: Remarks / Defect ID
A2: TC-SETUP-101 | B2: Installation | C2: Python runtime | D2: Python installs with 'Add python.exe to PATH' ticked | E2: P1 - Critical | F2: Functional | G2: A clean Windows 10/11 machine with no Python installed. | H2: 1. Open https://www.python.org/downloads/ 2. Download and run the installer 3. On the FIRST screen tick 'Add python.exe to PATH' 4. Click 'Install Now' and wait for it to finish 5. Open Command Prompt and run: python --version | I2: Latest Python 3.11+ installer | J2: Installation completes. 'python --version' prints a version number (e.g. Python 3.12.x) instead of 'not recognised'. | L2: Not Run
A3: TC-SETUP-102 | B3: Installation | C3: Python runtime | D3: Setup script detects a missing PATH entry and refuses to continue | E3: P2 - High | F3: Negative | G3: Python installed WITHOUT the PATH checkbox ticked. | H3: 1. Double-click setup-tester.bat 2. Read the message shown | I3: setup-tester.bat | J3: Script stops with a clear message that Python is not installed / not on PATH, and tells the user to redo Step 1. It does NOT continue and does NOT leave a half-installed state. | L3: Not Run
A4: TC-SETUP-103 | B4: Installation | C4: Dependencies | D4: setup-tester.bat installs engine dependencies successfully | E4: P1 - Critical | F4: Functional | G4: Python is installed with PATH ticked. | H4: 1. Double-click setup-tester.bat 2. Wait for the script to finish 3. Read the final message | I4: setup-tester.bat | J4: The window ends with the banner 'SUCCESS - setup is complete.' and no red error text. | L4: Not Run
A5: TC-SETUP-104 | B5: Installation | C5: App installer | D5: Charticks installs from the .exe past the SmartScreen warning | E5: P1 - Critical | F5: Functional | G5: Charticks-Setup-0.1.0.exe has been downloaded. | H5: 1. Double-click Charticks-Setup-0.1.0.exe 2. On 'Windows protected your PC' click 'More info' then 'Run anyway' 3. Complete the installer | I5: Charticks-Setup-0.1.0.exe | J5: Installer completes. A Charticks shortcut appears on the Desktop / Start Menu. | L5: Not Run
A6: TC-SETUP-105 | B6: Installation | C6: First launch | D6: App opens and the engine starts within ~10 seconds | E6: P1 - Critical | F6: Functional | G6: Charticks is installed. | H6: 1. Launch Charticks from the Desktop 2. Wait up to 15 seconds 3. Look at the top-left status area | I6: - | J6: Window opens; the bridge indicator changes from 'Connecting...' to 'Bridge live'. No blank/white screen. | L6: Not Run
A7: TC-SETUP-106 | B7: Installation | C7: First launch | D7: App still opens (degraded) when Python is missing | E7: P2 - High | F7: Negative | G7: Python is NOT installed. | H7: 1. Launch Charticks 2. Observe the status bar and the panels | I7: - | J7: App window opens rather than crashing; the bridge shows it is not connected and panels are empty. The user is not shown a raw stack trace. | L7: Not Run
A8: TC-SETUP-107 | B8: Installation | C8: Logs | D8: Log files are written to the documented folder | E8: P3 - Medium | F8: Functional | G8: Charticks has been launched at least once. | H8: 1. Paste %LOCALAPPDATA%\Programs\charticks\resources\sidecar\logs into File Explorer 2. Open the newest dated folder | I8: - | J8: A dated folder exists containing app.log with readable entries for the current session. | L8: Not Run
A9: TC-SETUP-108 | B9: Installation | C9: Logs | D9: Log files never contain broker passwords / API keys / tokens | E9: P1 - Critical | F9: Security | G9: A broker account has been connected at least once. | H9: 1. Open the newest log folder 2. Open app.log in Notepad 3. Use Ctrl+F to search for the password, API key, TOTP and access token you entered | I9: The credentials used to connect | J9: None of the secret values appear anywhere in the log file. | L9: Not Run
A10: TC-UI-201 | B10: App Shell | C10: Navigation | D10: All six screens open from the left rail | E10: P1 - Critical | F10: UI / UX | G10: Charticks is installed and open; sidecar (engine) is running. | H10: 1. Click each rail icon in turn: Home, Orders, Positions, Strategies, Brokers, Settings 2. Confirm the screen changes each time | I10: - | J10: Each click loads the matching screen, the active icon is highlighted, and no screen is blank or throws an error. | L10: Not Run
A11: TC-UI-202 | B11: App Shell | C11: Status bar | D11: Bridge indicator shows 'Bridge live' when the engine is running | E11: P1 - Critical | F11: UI / UX | G11: Charticks is installed and open; sidecar (engine) is running. | H11: 1. Look at the top-left of the status bar | I11: - | J11: A green dot with 'Bridge live'. If the engine is stopped it reads 'Connecting...' with a dimmed dot. | L11: Not Run
A12: TC-UI-203 | B12: App Shell | C12: Status bar | D12: Clock ticks in real time | E12: P3 - Medium | F12: UI / UX | G12: Charticks is installed and open; sidecar (engine) is running. | H12: 1. Watch the clock on the right of the status bar for 5 seconds | I12: - | J12: The time updates every second in 24-hour format. | L12: Not Run
A13: TC-UI-204 | B13: App Shell | C13: Theme | D13: Theme toggles between dark and light and stays applied | E13: P2 - High | F13: UI / UX | G13: Charticks is installed and open; sidecar (engine) is running. | H13: 1. Click the sun/moon button at the top right 2. Observe the whole window 3. Click it again | I13: - | J13: The entire UI switches theme (not just part of it), the icon flips, and switching back restores the original theme. Text stays readable in both. | L13: Not Run
... A185: TC-USE-305 | B185: Usability | C185: Regression | D185: A full happy-path trade cycle works end to end | E185: P1 - Critical | F185: Integration | G185: Trading mode badge shows 'Paper'. Market is open and a broker is connected. | H185: 1. Connect a broker 2. Pick an index and expiry 3. Buy 1 lot at market 4. Edit the SL 5. Add a lot 6. Exit 50% 7. Square off the rest 8. Check Orders and Trade Book | I185: - | J185: Every step behaves as specified above and the order/trade history matches exactly what was done, with quantities and P&L consistent throughout. | L185: Not Run

Sheet Summary
B2: Execution Summary
B4: Total test cases | C4: 184
B5: Pass | C5: =COUNTIF('Test Cases'!L2:L185,"Pass")
B6: Fail | C6: =COUNTIF('Test Cases'!L2:L185,"Fail")
B7: Blocked | C7: =COUNTIF('Test Cases'!L2:L185,"Blocked")
B8: Not Run | C8: =COUNTIF('Test Cases'!L2:L185,"Not Run")
B9: N/A | C9: =COUNTIF('Test Cases'!L2:L185,"N/A")
B10: Pass rate (of executed) | C10: =IFERROR(COUNTIF('Test Cases'!L2:L185,"Pass")/(COUNTIF('Test Cases'!L2:L185,"Pass")+COUNTIF('Test Cases'!L2:L185,"Fail")),"-")
B12: Failures by severity
B13: Critical | C13: =COUNTIFS('Test Cases'!L2:L185,"Fail",'Test Cases'!M2:M185,"Critical")
B14: High | C14: =COUNTIFS('Test Cases'!L2:L185,"Fail",'Test Cases'!M2:M185,"High")
B15: Medium | C15: =COUNTIFS('Test Cases'!L2:L185,"Fail",'Test Cases'!M2:M185,"Medium")
B16: Low | C16: =COUNTIFS('Test Cases'!L2:L185,"Fail",'Test Cases'!M2:M185,"Low")
B18: Cases by module | D18: Passed
B19: Installation | C19: =COUNTIF('Test Cases'!B2:B185,"Installation") | D19: =COUNTIFS('Test Cases'!B2:B185,"Installation",'Test Cases'!L2:L185,"Pass")
B20: App Shell | C20: =COUNTIF('Test Cases'!B2:B185,"App Shell") | D20: =COUNTIFS('Test Cases'!B2:B185,"App Shell",'Test Cases'!L2:L185,"Pass")
B21: Brokers | C21: =COUNTIF('Test Cases'!B2:B185,"Brokers") | D21: =COUNTIFS('Test Cases'!B2:B185,"Brokers",'Test Cases'!L2:L185,"Pass")
B22: Market Data | C22: =COUNTIF('Test Cases'!B2:B185,"Market Data") | D22: =COUNTIFS('Test Cases'!B2:B185,"Market Data",'Test Cases'!L2:L185,"Pass")
B23: Option Chain | C23: =COUNTIF('Test Cases'!B2:B185,"Option Chain") | D23: =COUNTIFS('Test Cases'!B2:B185,"Option Chain",'Test Cases'!L2:L185,"Pass")
B24: Order Entry | C24: =COUNTIF('Test Cases'!B2:B185,"Order Entry") | D24: =COUNTIFS('Test Cases'!B2:B185,"Order Entry",'Test Cases'!L2:L185,"Pass")
B25: Market Hours | C25: =COUNTIF('Test Cases'!B2:B185,"Market Hours") | D25: =COUNTIFS('Test Cases'!B2:B185,"Market Hours",'Test Cases'!L2:L185,"Pass")
B26: Positions | C26: =COUNTIF('Test Cases'!B2:B185,"Positions") | D26: =COUNTIFS('Test Cases'!B2:B185,"Positions",'Test Cases'!L2:L185,"Pass")
B27: Roll | C27: =COUNTIF('Test Cases'!B2:B185,"Roll") | D27: =COUNTIFS('Test Cases'!B2:B185,"Roll",'Test Cases'!L2:L185,"Pass")
B28: Orders | C28: =COUNTIF('Test Cases'!B2:B185,"Orders") | D28: =COUNTIFS('Test Cases'!B2:B185,"Orders",'Test Cases'!L2:L185,"Pass")
B29: Risk Rules | C29: =COUNTIF('Test Cases'!B2:B185,"Risk Rules") | D29: =COUNTIFS('Test Cases'!B2:B185,"Risk Rules",'Test Cases'!L2:L185,"Pass")
B30: Portfolio Trail | C30: =COUNTIF('Test Cases'!B2:B185,"Portfolio Trail") | D30: =COUNTIFS('Test Cases'!B2:B185,"Portfolio Trail",'Test Cases'!L2:L185,"Pass")
B31: Session Limits | C31: =COUNTIF('Test Cases'!B2:B185,"Session Limits") | D31: =COUNTIFS('Test Cases'!B2:B185,"Session Limits",'Test Cases'!L2:L185,"Pass")
B32: Max Position | C32: =COUNTIF('Test Cases'!B2:B185,"Max Position") | D32: =COUNTIFS('Test Cases'!B2:B185,"Max Position",'Test Cases'!L2:L185,"Pass")
B33: Settings | C33: =COUNTIF('Test Cases'!B2:B185,"Settings") | D33: =COUNTIFS('Test Cases'!B2:B185,"Settings",'Test Cases'!L2:L185,"Pass")
B34: Trading Mode | C34: =COUNTIF('Test Cases'!B2:B185,"Trading Mode") | D34: =COUNTIFS('Test Cases'!B2:B185,"Trading Mode",'Test Cases'!L2:L185,"Pass")
B35: Order Splitting | C35: =COUNTIF('Test Cases'!B2:B185,"Order Splitting") | D35: =COUNTIFS('Test Cases'!B2:B185,"Order Splitting",'Test Cases'!L2:L185,"Pass")
B36: Reliability | C36: =COUNTIF('Test Cases'!B2:B185,"Reliability") | D36: =COUNTIFS('Test Cases'!B2:B185,"Reliability",'Test Cases'!L2:L185,"Pass")
B37: Security | C37: =COUNTIF('Test Cases'!B2:B185,"Security") | D37: =COUNTIFS('Test Cases'!B2:B185,"Security",'Test Cases'!L2:L185,"Pass")
B38: Usability | C38: =COUNTIF('Test Cases'!B2:B185,"Usability") | D38: =COUNTIFS('Test Cases'!B2:B185,"Usability",'Test Cases'!L2:L185,"Pass")

Sheet Defect Log
A1: Defect ID | B1: Linked TC ID | C1: Module | D1: Summary | E1: Severity | F1: Priority | G1: Steps to Reproduce | H1: Expected | I1: Actual | J1: Environment | K1: Reported By | L1: Date | M1: Status | N1: Screenshot / Log attached
